[
  {
    "title": "合建分屋EP10-熱門問答合建分屋稅務十大常見問題",
    "url": "/blog/2025-09-18-tax.html",
    "date": "2025-09-18",
    "summary": "合建分屋EP10-熱門問答合建分屋稅務十大常見問題 - 霍爾果斯會計師事務所專業服務，提供稅務相關相關諮詢",
    "category": "tax",
    "category_name": "稅務相關",
    "tags": [
      {
        "slug": "tax",
        "name": "Tax"
      }
    ],
    "image": "/assets/images/blog/default.jpg",
    "is_series": false
  },
  {
    "title": "合建分屋EP9-實務策略合建分屋稅負優化與常見錯誤",
    "url": "/blog/2025-09-11-practice-tax.html",
    "date": "2025-09-11",
    "summary": "合建分屋EP9-實務策略合建分屋稅負優化與常見錯誤 - 霍爾果斯會計師事務所專業服務，提供稅務相關相關諮詢",
    "category": "tax",
    "category_name": "稅務相關",
    "tags": [
      {
        "slug": "practice",
        "name": "Practice"
      },
      {
        "slug": "tax",
        "name": "Tax"
      }
    ],
    "image": "/assets/images/blog/default.jpg",
    "is_series": false
  },
  {
    "title": "合建分屋EP8-建設公司II發票開立規定與營業稅處理",
    "url": "/blog/2025-09-04-business-tax-tax.html",
    "date": "2025-09-04",
    "summary": "合建分屋EP8-建設公司II發票開立規定與營業稅處理 - 霍爾果斯會計師事務所專業服務，提供稅務相關相關諮詢",
    "category": "tax",
    "category_name": "稅務相關",
    "tags": [
      {
        "slug": "business-tax",
        "name": "Business Tax"
      },
      {
        "slug": "tax",
        "name": "Tax"
      }
    ],
    "image": "/assets/images/blog/default.jpg",
    "is_series": false
  }
]