{
  "title": "遺贈稅申報常見錯誤與案例分享",
  "summary": "遺產及贈與稅的申報因涉及法規複雜且不甚熟悉，許多納稅義務人經常因理解錯誤或疏忽而導致短漏報情形，不僅需補繳稅款，更可能面臨罰鍰處罰。本文彙整遺贈稅申報實務中最常見的錯誤態樣及案例分享，協助讀者避免踩雷，順利完成申報。",
  "date": "2025-02-21",
  "is_series": true,
  "series_name": "遺產及贈與稅與財富傳承",
  "episode": 12,
  "original_filename": "2025-02-21-遺產及贈與稅與財富傳承EP12-遺贈稅申報常見錯誤與案例分享.docx",
  "html_path": "blog/2025-02-21-taxation-inheritance-gift-bequest-tax-filing-common-errors-and-case-sharing-inherita.html",
  "classification": {
    "main_category": "稅務服務",
    "main_category_code": "taxation",
    "subcategory": "遺產贈與",
    "subcategory_code": "inheritance-gift",
    "confidence": 88
  },
  "tags": [
    {
      "name": "稅務服務",
      "slug": "tag-稅務服務"
    },
    {
      "name": "申報",
      "slug": "declaration"
    },
    {
      "name": "遺產",
      "slug": "tag-遺產"
    }
  ]
}