{
  "title": "【營利事業I】營利事業地主稅率與持有期間認定EP5",
  "summary": "發布日期：2025-08-14",
  "date": "2025-08-14",
  "is_series": true,
  "series_name": "合建分屋",
  "episode": 5,
  "original_filename": "2025-08-14-合建分屋EP5-營利事業I營利事業地主稅率與持有期間認定.docx",
  "html_path": "blog/2025-08-14-taxation-real-estate-tax-profitmaking-business-i-profitmaking-business-landlord-tax-.html",
  "classification": {
    "main_category": "稅務服務",
    "main_category_code": "taxation",
    "subcategory": "不動產稅務",
    "subcategory_code": "real-estate-tax",
    "confidence": 61
  },
  "tags": [
    {
      "name": "稅率",
      "slug": "tax-rate"
    },
    {
      "name": "營利事業",
      "slug": "tag-營利事業"
    },
    {
      "name": "取得",
      "slug": "acquisition"
    }
  ]
}